widget_bandsplot/__init__.py
widget_bandsplot/static/widget.css
widget_bandsplot/static/widget.js
widget_bandsplot-0.7.4.dist-info/METADATA
widget_bandsplot-0.7.4.dist-info/WHEEL
widget_bandsplot-0.7.4.dist-info/licenses/LICENSE.txt
widget_bandsplot-0.7.4.dist-info/RECORD
