Metadata-Version: 2.3
Name: widget-bandsplot
Version: 0.7.4
Summary: A Jupyter widget to plot band structure and density of states.
Project-URL: Home, https://www.osscar.org/
Project-URL: Source, https://github.com/osscar-org/widget-bandsplot
Author: The OSSCAR team
License: BSD 3-Clause License
License-File: LICENSE.txt
Keywords: anywidget,electronic-structure,jupyter,jupyterlab,osscar,phonons,widget
Classifier: Development Status :: 5 - Production/Stable
Classifier: Framework :: Jupyter
Classifier: Framework :: Jupyter :: JupyterLab
Classifier: Programming Language :: Python
Classifier: Programming Language :: Python :: 3.9
Classifier: Programming Language :: Python :: 3.10
Classifier: Programming Language :: Python :: 3.11
Classifier: Topic :: Scientific/Engineering
Requires-Python: >=3.9
Requires-Dist: anywidget~=0.9.13
Provides-Extra: dev
Requires-Dist: bumpver>=2023.1129; extra == 'dev'
Requires-Dist: jupyterlab; extra == 'dev'
Requires-Dist: notebook; extra == 'dev'
Requires-Dist: watchfiles; extra == 'dev'
